longdocfactscore/ldfacts.py
longdocfactscore-1.0.0.dist-info/LICENSE
longdocfactscore-1.0.0.dist-info/METADATA
longdocfactscore-1.0.0.dist-info/WHEEL
longdocfactscore-1.0.0.dist-info/top_level.txt
longdocfactscore-1.0.0.dist-info/RECORD
