Metadata-Version: 2.1
Name: longdocfactscore
Version: 1.0.0
Summary: LongDocFACTScore: A framework for evaluating factual consistency of long document abstractive summarisation and the LongSciVerify data set
Author: Jennifer A Bishop
Project-URL: Homepage, https://github.com/jbshp/LongDocFACTScore
Project-URL: Issues, https://github.com/jbshp/LongDocFACTScore/issues
Classifier: Programming Language :: Python :: 3
Classifier: License :: OSI Approved :: MIT License
Classifier: Operating System :: OS Independent
Requires-Python: >=3.8
License-File: LICENSE
Requires-Dist: nltk
Requires-Dist: numpy
Requires-Dist: sentence-transformers
Requires-Dist: torch
Requires-Dist: transformers
Requires-Dist: pandas
